{"width":2048,"SubTexture":[{"width":256,"y":1033,"height":256,"name":"Smoke_009","x":1},{"width":146,"y":328,"height":117,"name":"H46 (5)","x":1807},{"width":146,"y":566,"height":117,"name":"H46 (7)","x":1807},{"width":146,"y":209,"height":117,"name":"H46 (6)","x":1807},{"width":146,"y":447,"height":117,"name":"H46 (4)","x":1807},{"width":128,"y":1807,"height":128,"name":"RotateLight_034","x":131},{"width":128,"y":1807,"height":128,"name":"B_BackColor002_emis","x":1},{"width":239,"y":1,"height":206,"name":"Stone/Stone","x":1807},{"width":43,"y":1980,"height":34,"name":"Stone/Stone_20","x":164},{"width":25,"y":775,"height":35,"name":"Stone/Stone_19","x":2017},{"width":53,"y":1937,"height":53,"name":"Stone/Stone_18","x":67},{"width":81,"y":384,"height":83,"name":"Stone/Stone_15","x":1955},{"width":105,"y":685,"height":88,"name":"Stone/Stone_14","x":1937},{"width":75,"y":209,"height":94,"name":"Stone/Stone_13","x":1955},{"width":49,"y":2010,"height":37,"name":"Stone/Stone_12","x":1},{"width":64,"y":1937,"height":71,"name":"Stone/Stone_11","x":1},{"width":33,"y":1937,"height":32,"name":"Stone/Stone_10","x":170},{"width":58,"y":1992,"height":47,"name":"Stone/Stone_17","x":67},{"width":35,"y":1980,"height":42,"name":"Stone/Stone_16","x":127},{"width":75,"y":607,"height":70,"name":"Stone/Stone_9","x":1955},{"width":46,"y":1937,"height":41,"name":"Stone/Stone_8","x":122},{"width":22,"y":841,"height":18,"name":"Stone/Stone_7","x":2017},{"width":78,"y":775,"height":66,"name":"Stone/Stone_4","x":1937},{"width":82,"y":538,"height":67,"name":"Stone/Stone_3","x":1955},{"width":91,"y":305,"height":77,"name":"Stone/Stone_2","x":1955},{"width":18,"y":2024,"height":14,"name":"Stone/Stone_6","x":127},{"width":26,"y":812,"height":27,"name":"Stone/Stone_5","x":2017},{"width":91,"y":469,"height":67,"name":"Stone/Stone_1","x":1955},{"width":128,"y":685,"height":128,"name":"Effects_Textures_1529-1","x":1807},{"width":256,"y":1,"height":256,"name":"Boom/M49 (11)","x":517},{"width":256,"y":1,"height":256,"name":"Boom/M49 (17)","x":775},{"width":256,"y":259,"height":256,"name":"Boom/M49 (30)","x":517},{"width":256,"y":1,"height":256,"name":"Boom/M49 (24)","x":1549},{"width":256,"y":775,"height":256,"name":"Boom/M49 (4)","x":1},{"width":256,"y":1,"height":256,"name":"Boom/M49 (31)","x":1033},{"width":256,"y":517,"height":256,"name":"Boom/M49 (10)","x":1},{"width":256,"y":1,"height":256,"name":"Boom/M49 (16)","x":1},{"width":256,"y":517,"height":256,"name":"Boom/M49 (27)","x":1549},{"width":256,"y":259,"height":256,"name":"Boom/M49 (29)","x":1291},{"width":256,"y":517,"height":256,"name":"Boom/M49 (26)","x":1033},{"width":256,"y":259,"height":256,"name":"Boom/M49 (23)","x":259},{"width":256,"y":775,"height":256,"name":"Boom/M49 (25)","x":517},{"width":256,"y":1549,"height":256,"name":"Boom/M49 (15)","x":259},{"width":256,"y":1,"height":256,"name":"Boom/M49 (22)","x":259},{"width":256,"y":517,"height":256,"name":"Boom/M49 (21)","x":517},{"width":256,"y":1549,"height":256,"name":"Boom/M49 (9)","x":1},{"width":256,"y":1,"height":256,"name":"Boom/M49 (3)","x":1291},{"width":256,"y":775,"height":256,"name":"Boom/M49 (14)","x":775},{"width":256,"y":259,"height":256,"name":"Boom/M49 (13)","x":775},{"width":256,"y":1291,"height":256,"name":"Boom/M49 (32)","x":259},{"width":256,"y":775,"height":256,"name":"Boom/M49 (2)","x":259},{"width":256,"y":1549,"height":256,"name":"Boom/M49 (8)","x":517},{"width":256,"y":517,"height":256,"name":"Boom/M49 (7)","x":775},{"width":256,"y":259,"height":256,"name":"Boom/M49 (20)","x":1033},{"width":256,"y":1291,"height":256,"name":"Boom/M49 (1)","x":517},{"width":256,"y":1033,"height":256,"name":"Boom/M49 (6)","x":517},{"width":256,"y":259,"height":256,"name":"Boom/M49 (12)","x":1},{"width":256,"y":517,"height":256,"name":"Boom/M49 (19)","x":259},{"width":256,"y":259,"height":256,"name":"Boom/M49 (18)","x":1549},{"width":256,"y":1033,"height":256,"name":"Boom/M49 (28)","x":259},{"width":256,"y":517,"height":256,"name":"Boom/M49 (5)","x":1291},{"width":256,"y":1291,"height":256,"name":"A_RingGlow002_emis","x":1}],"height":2048,"name":"bomb_wild","imagePath":"bomb_wild_tex.png"}