{"skeleton":{"hash":"rsEobhse0KqSKde58FTdYf3Kktc","spine":"3.8.99","x":-42.83,"y":-10.03,"width":84,"height":142,"images":"./images/","audio":"C:/Users/pc/OneDrive/Desktop/dem so bat dau"},"bones":[{"name":"root"},{"name":"Group 39","parent":"root","length":70.72,"rotation":90.59,"x":0.6,"y":36.54},{"name":"Group 40","parent":"root","length":72.26,"rotation":87.11,"x":-1.59,"y":31.44},{"name":"Group 41","parent":"root","length":86.1,"rotation":92.43,"x":2.79,"y":29.25}],"slots":[{"name":"Group 39","bone":"Group 39","attachment":"Group 39"},{"name":"Group 40","bone":"Group 40","color":"ffffff00","attachment":"Group 40"},{"name":"Group 41","bone":"Group 41","color":"ffffff00","attachment":"Group 41"}],"skins":[{"name":"default","attachments":{"Group 39":{"Group 39":{"x":24.44,"y":1.18,"rotation":-90.59,"width":84,"height":142}},"Group 40":{"Group 40":{"x":31,"y":1.44,"rotation":-87.11,"width":81,"height":139}},"Group 41":{"Group 41":{"x":32.68,"y":10.12,"rotation":-92.43,"width":64,"height":137}}}}],"animations":{"animation":{"slots":{"Group 39":{"color":[{"color":"ffffff00","curve":"stepped"},{"time":0.1667,"color":"ffffff00"},{"time":0.3333,"color":"ffffffff","curve":"stepped"},{"time":0.6667,"color":"ffffffff"},{"time":0.8333,"color":"ffffff00"}]},"Group 40":{"color":[{"time":0.8333,"color":"ffffff00"},{"time":1,"color":"ffffffff","curve":"stepped"},{"time":1.3333,"color":"ffffffff"},{"time":1.5,"color":"ffffff00"}]},"Group 41":{"color":[{"time":1.5,"color":"ffffff00"},{"time":1.6667,"color":"ffffffff","curve":"stepped"},{"time":2,"color":"ffffffff"},{"time":2.1667,"color":"ffffff00"}]}},"bones":{"Group 41":{"scale":[{},{"time":1.5,"x":1.664,"y":1.664},{"time":1.6667,"curve":"stepped"},{"time":2},{"time":2.1667,"x":1.664,"y":1.664},{"time":2.3333}]},"Group 40":{"scale":[{},{"time":0.8333,"x":1.727,"y":1.727},{"time":1,"curve":"stepped"},{"time":1.3333},{"time":1.5,"x":1.727,"y":1.727},{"time":2.3333}]},"Group 39":{"scale":[{},{"time":0.1667,"x":1.765,"y":1.765},{"time":0.3333,"curve":"stepped"},{"time":0.6667},{"time":0.8333,"x":1.765,"y":1.765},{"time":2.3333}]}}}}}